Metadata-Version: 1.0
Name: gauss-bin-prob-distrib
Version: 0.1
Summary: Gaussian and Binomial distributions
Home-page: UNKNOWN
Author: Boukary Ouedraogo
Author-email: abhou16@gmail.com
License: UNKNOWN
Platform: UNKNOWN
